figeno/__init__.py
figeno/ase.py
figeno/bam.py
figeno/figeno.py
figeno/genes.py
figeno/track_alignments.py
figeno/track_ase.py
figeno/track_basemodfreq.py
figeno/track_bed.py
figeno/track_bigwig.py
figeno/track_chr.py
figeno/track_copynumber.py
figeno/track_coverage.py
figeno/track_genes.py
figeno/track_hic.py
figeno/track_sv.py
figeno/utils.py
figeno/cli/__init__.py
figeno/cli/cli.py
figeno/cli/gui.py
figeno/cli/init.py
figeno/cli/make.py
figeno/data/__init__.py
figeno/data/hg19_cytobands.tsv
figeno/data/hg19_genes.txt.gz
figeno/data/hg38_cytobands.tsv
figeno/data/hg38_genes.txt.gz
figeno/data/mm10_cytobands.tsv
figeno/data/mm10_genes.txt.gz
figeno/gui/__init__.py
figeno/gui/gui_browser.py
figeno/gui/gui_server.py
figeno/gui/gui_webview.py
figeno/gui/build/asset-manifest.json
figeno/gui/build/figeno_icon.png
figeno/gui/build/index.html
figeno/gui/build/manifest.json
figeno/gui/build/static/css/main.76a8e97c.css
figeno/gui/build/static/css/main.76a8e97c.css.map
figeno/gui/build/static/js/main.ea92c059.js
figeno/gui/build/static/js/main.ea92c059.js.LICENSE.txt
figeno/gui/build/static/js/main.ea92c059.js.map
figeno/gui/build/static/media/template_asm.55717ae257ceeaeb8333.png
figeno/gui/build/static/media/template_bigwig.09eec339ebda266768bb.png
figeno/gui/build/static/media/template_hic.a82d056b5818faabdef7.png
figeno/gui/build/static/media/template_wgs_chr.58a28a28c2d4a1a56f3e.png
figeno/gui/build/static/media/template_wgs_circos.ecc318c406b140354064.png
figeno-1.9.0.dist-info/LICENSE
figeno-1.9.0.dist-info/METADATA
figeno-1.9.0.dist-info/WHEEL
figeno-1.9.0.dist-info/entry_points.txt
figeno-1.9.0.dist-info/top_level.txt
figeno-1.9.0.dist-info/RECORD
