Metadata-Version: 2.1
Name: figeno
Version: 1.9.0
Summary: Package for generating genomics figures.
Author: Etienne Sollier
Project-URL: Homepage, https://github.com/CompEpigen/figeno
Classifier: Programming Language :: Python :: 3
Classifier: Operating System :: OS Independent
Classifier: License :: OSI Approved :: GNU General Public License v3 (GPLv3)
Classifier: Intended Audience :: Science/Research
Classifier: Topic :: Scientific/Engineering :: Bio-Informatics
Requires-Python: >=3.7
License-File: LICENSE
Requires-Dist: numpy <2.0,>=1.10.0
Requires-Dist: pandas >=1.3.0
Requires-Dist: matplotlib >=3.4.3
Requires-Dist: importlib-resources >=5.0.0
Requires-Dist: pysam >=0.16.0
Requires-Dist: pyBigWig >=0.3.18
Requires-Dist: vcfpy >=0.13.5
Requires-Dist: cooler >=0.9.1
Requires-Dist: Flask >=2.2.5
Requires-Dist: filedialpy >=1.2.0
Requires-Dist: pywebview >=4.4.1
